[{"pos":1,"bib":460,"name":"HIROTAKA TANIMOTO","nat":"—","cat":"M 20–39","time":"02:24:13","sec":8653},{"pos":2,"bib":114,"name":"PHIL COSTLEY","nat":"—","cat":"M 40–49","time":"02:27:27","sec":8847},{"pos":3,"bib":299,"name":"JOSH MAISEY","nat":"—","cat":"M 20–39","time":"02:27:52","sec":8872},{"pos":4,"bib":375,"name":"JASON PALMER","nat":"—","cat":"M 20–39","time":"02:30:50","sec":9050},{"pos":5,"bib":212,"name":"BEN HARRIS","nat":"—","cat":"M 20–39","time":"02:34:24","sec":9264},{"pos":6,"bib":380,"name":"DAVE PARSONS","nat":"—","cat":"M 20–39","time":"02:35:07","sec":9307},{"pos":7,"bib":542,"name":"BEN RUTHE","nat":"—","cat":"M 20–39","time":"02:35:39","sec":9339},{"pos":8,"bib":91,"name":"GLEN CHISHOLM","nat":"—","cat":"M 20–39","time":"02:39:47","sec":9587},{"pos":9,"bib":444,"name":"RYAN STACEY","nat":"—","cat":"M 20–39","time":"02:41:59","sec":9719},{"pos":10,"bib":344,"name":"JACK MOODY","nat":"—","cat":"M 20–39","time":"02:42:47","sec":9767},{"pos":11,"bib":254,"name":"CHRIS KELLY","nat":"—","cat":"M 20–39","time":"02:44:34","sec":9874},{"pos":12,"bib":484,"name":"BEN TWYMAN","nat":"—","cat":"M 20–39","time":"02:44:44","sec":9884},{"pos":13,"bib":305,"name":"ALICE MASON","nat":"—","cat":"W 20–39","time":"02:45:43","sec":9943},{"pos":14,"bib":398,"name":"ROBERT PRENDERGAST","nat":"—","cat":"M 20–39","time":"02:48:44","sec":10124},{"pos":15,"bib":447,"name":"GAVIN STEVENS","nat":"—","cat":"M 50–59","time":"02:48:57","sec":10137},{"pos":16,"bib":4,"name":"MEL AITKEN","nat":"—","cat":"W 20–39","time":"02:49:13","sec":10153},{"pos":17,"bib":291,"name":"MARTIN LUKES","nat":"—","cat":"M 40–49","time":"02:50:12","sec":10212},{"pos":18,"bib":238,"name":"LIZA HUNTER-GALVAN","nat":"—","cat":"W 40–49","time":"02:50:38","sec":10238},{"pos":19,"bib":540,"name":"BEN WREFORD","nat":"—","cat":"M 20–39","time":"02:51:15","sec":10275},{"pos":20,"bib":416,"name":"GABRIEL ROACH","nat":"—","cat":"M 20–39","time":"02:51:22","sec":10282},{"pos":21,"bib":106,"name":"ANTHONY COLLIE","nat":"—","cat":"M 40–49","time":"02:52:25","sec":10345},{"pos":22,"bib":482,"name":"JEREMY TREVATHAN","nat":"—","cat":"M 20–39","time":"02:53:17","sec":10397},{"pos":23,"bib":48,"name":"CARL BEVINS","nat":"—","cat":"M 20–39","time":"02:53:26","sec":10406},{"pos":24,"bib":115,"name":"ALEX COWDEN","nat":"—","cat":"M 20–39","time":"02:54:16","sec":10456},{"pos":25,"bib":97,"name":"KENNY CLARK","nat":"—","cat":"M 20–39","time":"02:54:21","sec":10461},{"pos":26,"bib":564,"name":"TIM WRIGHT","nat":"—","cat":"M 40–49","time":"02:55:51","sec":10551},{"pos":27,"bib":489,"name":"KLAARTJE VAN SCHIE","nat":"—","cat":"W 20–39","time":"02:56:53","sec":10613},{"pos":28,"bib":567,"name":"CRAIG PETERS","nat":"—","cat":"M 20–39","time":"02:57:38","sec":10658},{"pos":29,"bib":354,"name":"NIGEL MORRIS","nat":"—","cat":"M 20–39","time":"02:58:10","sec":10690},{"pos":30,"bib":45,"name":"DANIEL BENNETT","nat":"—","cat":"M 20–39","time":"02:59:49","sec":10789},{"pos":31,"bib":123,"name":"MATTHEW CUTLER-WELSH","nat":"—","cat":"M 20–39","time":"02:59:59","sec":10799},{"pos":32,"bib":66,"name":"TIM BRYANT","nat":"—","cat":"M 20–39","time":"03:00:47","sec":10847},{"pos":33,"bib":249,"name":"PHILL JONES","nat":"—","cat":"M 20–39","time":"03:00:49","sec":10849},{"pos":34,"bib":56,"name":"GUY BONNER","nat":"—","cat":"M 20–39","time":"03:01:05","sec":10865},{"pos":35,"bib":211,"name":"ALEX HARRINGTON","nat":"—","cat":"M 20–39","time":"03:01:21","sec":10881},{"pos":36,"bib":59,"name":"ANDREW BRADY","nat":"—","cat":"M 20–39","time":"03:01:31","sec":10891},{"pos":37,"bib":28,"name":"DANNY BAILLIE","nat":"—","cat":"M 40–49","time":"03:02:23","sec":10943},{"pos":38,"bib":298,"name":"MARSHALL MAINE","nat":"—","cat":"M 40–49","time":"03:02:24","sec":10944},{"pos":39,"bib":18,"name":"JAYDEN ANKER","nat":"—","cat":"M 20–39","time":"03:02:31","sec":10951},{"pos":40,"bib":575,"name":"KELVIN ENTWISLE","nat":"—","cat":"M 20–39","time":"03:02:49","sec":10969},{"pos":41,"bib":336,"name":"NATHAN MERCURIO","nat":"—","cat":"M 20–39","time":"03:03:24","sec":11004},{"pos":42,"bib":486,"name":"CLINT VAN DER MESCHT","nat":"—","cat":"M 40–49","time":"03:03:45","sec":11025},{"pos":43,"bib":178,"name":"JARROD GIBSON","nat":"—","cat":"M 40–49","time":"03:03:50","sec":11030},{"pos":44,"bib":281,"name":"SHANNON-LEIGH LITT","nat":"—","cat":"W 20–39","time":"03:03:59","sec":11039},{"pos":45,"bib":250,"name":"HIDEYUKI KANAYA","nat":"—","cat":"M 40–49","time":"03:03:59","sec":11039},{"pos":46,"bib":232,"name":"CHRISTOPHER HOLMES","nat":"—","cat":"M 40–49","time":"03:05:14","sec":11114},{"pos":47,"bib":1,"name":"MICHAEL ABERNETHY","nat":"—","cat":"M 20–39","time":"03:05:24","sec":11124},{"pos":48,"bib":112,"name":"SHAUN COOPER","nat":"—","cat":"M 40–49","time":"03:05:33","sec":11133},{"pos":49,"bib":570,"name":"SCOTT HOTHAM","nat":"—","cat":"M 40–49","time":"03:05:37","sec":11137},{"pos":50,"bib":37,"name":"JAMES BAYLY","nat":"—","cat":"M 20–39","time":"03:05:47","sec":11147},{"pos":51,"bib":227,"name":"SEAN HEPBURN","nat":"—","cat":"M 40–49","time":"03:07:16","sec":11236},{"pos":52,"bib":125,"name":"MICHAEL DALL","nat":"—","cat":"M 40–49","time":"03:08:12","sec":11292},{"pos":53,"bib":90,"name":"GUAN-DI CHIOU","nat":"—","cat":"M 20–39","time":"03:08:27","sec":11307},{"pos":54,"bib":325,"name":"ALEX MCKINNEY","nat":"—","cat":"M 20–39","time":"03:08:54","sec":11334},{"pos":55,"bib":536,"name":"HAYDEN ZERVOS","nat":"—","cat":"M 20–39","time":"03:09:38","sec":11378},{"pos":56,"bib":457,"name":"JARON TABAK","nat":"—","cat":"M 20–39","time":"03:09:51","sec":11391},{"pos":57,"bib":502,"name":"CHRIS WATSON","nat":"—","cat":"M 20–39","time":"03:10:35","sec":11435},{"pos":58,"bib":276,"name":"RICHARD LEARY","nat":"—","cat":"M 20–39","time":"03:10:36","sec":11436},{"pos":59,"bib":538,"name":"RUSSELL WORDSWORTH","nat":"—","cat":"M 20–39","time":"03:10:38","sec":11438},{"pos":60,"bib":147,"name":"STEVE DUXFIELD","nat":"—","cat":"M 50–59","time":"03:10:42","sec":11442},{"pos":61,"bib":529,"name":"SIMON WRIGHT","nat":"—","cat":"M 40–49","time":"03:11:36","sec":11496},{"pos":62,"bib":524,"name":"RYAN WOOD","nat":"—","cat":"M 20–39","time":"03:11:39","sec":11499},{"pos":63,"bib":421,"name":"J PAUL RONALDSON","nat":"—","cat":"M 50–59","time":"03:11:42","sec":11502},{"pos":64,"bib":367,"name":"MARK NORTH","nat":"—","cat":"M 20–39","time":"03:11:51","sec":11511},{"pos":65,"bib":219,"name":"JAMIE HAWKER","nat":"—","cat":"M 50–59","time":"03:12:52","sec":11572},{"pos":66,"bib":468,"name":"WILLIAM TENNENT","nat":"—","cat":"M 20–39","time":"03:13:06","sec":11586},{"pos":67,"bib":53,"name":"RAY BOARDMAN","nat":"—","cat":"M 20–39","time":"03:13:26","sec":11606},{"pos":68,"bib":338,"name":"ROLAND MEYER","nat":"—","cat":"M 50–59","time":"03:13:36","sec":11616},{"pos":69,"bib":319,"name":"MARTIN MCGUINNESS","nat":"—","cat":"M 40–49","time":"03:13:43","sec":11623},{"pos":70,"bib":440,"name":"TIMOTHY SMITH","nat":"—","cat":"M 20–39","time":"03:13:52","sec":11632},{"pos":71,"bib":156,"name":"FASMEL FAELDIN","nat":"—","cat":"M 40–49","time":"03:14:16","sec":11656},{"pos":72,"bib":357,"name":"DAWSON MUIR","nat":"—","cat":"M 40–49","time":"03:14:19","sec":11659},{"pos":73,"bib":528,"name":"BRENDAN WRIGHT","nat":"—","cat":"M 20–39","time":"03:14:25","sec":11665},{"pos":74,"bib":102,"name":"HAMISH COCKS","nat":"—","cat":"M 20–39","time":"03:14:28","sec":11668},{"pos":75,"bib":172,"name":"GRACIE FRASER","nat":"—","cat":"W 20–39","time":"03:14:54","sec":11694},{"pos":76,"bib":47,"name":"KIERON BERRY","nat":"—","cat":"M 40–49","time":"03:15:41","sec":11741},{"pos":77,"bib":155,"name":"GREG FACTOR","nat":"—","cat":"M 20–39","time":"03:16:42","sec":11802},{"pos":78,"bib":435,"name":"SARAH SINCLAIR","nat":"—","cat":"W 20–39","time":"03:16:43","sec":11803},{"pos":79,"bib":273,"name":"MARK LA ROCHE","nat":"—","cat":"M 40–49","time":"03:17:10","sec":11830},{"pos":80,"bib":554,"name":"KRISTIN FOSTER","nat":"—","cat":"M 20–39","time":"03:17:33","sec":11853},{"pos":81,"bib":395,"name":"JULIAN PHILLIPS","nat":"—","cat":"M 40–49","time":"03:17:35","sec":11855},{"pos":82,"bib":339,"name":"BRIAN MILES","nat":"—","cat":"M 40–49","time":"03:17:35","sec":11855},{"pos":83,"bib":169,"name":"BRENT FOSTER","nat":"—","cat":"M 40–49","time":"03:17:46","sec":11866},{"pos":84,"bib":413,"name":"ADRIAN RIEPEN","nat":"—","cat":"M 20–39","time":"03:17:56","sec":11876},{"pos":85,"bib":505,"name":"MARK WESTER","nat":"—","cat":"M 40–49","time":"03:18:14","sec":11894},{"pos":86,"bib":74,"name":"ISAAC BURWELL","nat":"—","cat":"M 20–39","time":"03:18:21","sec":11901},{"pos":87,"bib":414,"name":"MARK RIGBY","nat":"—","cat":"M 40–49","time":"03:18:31","sec":11911},{"pos":88,"bib":277,"name":"CARRIE LEE-PETERSEN","nat":"—","cat":"W 20–39","time":"03:18:46","sec":11926},{"pos":89,"bib":568,"name":"LEROY DE BEER","nat":"—","cat":"M 20–39","time":"03:18:59","sec":11939},{"pos":90,"bib":472,"name":"SCOTTY THORNTON","nat":"—","cat":"M 20–39","time":"03:19:14","sec":11954},{"pos":91,"bib":256,"name":"BEN KEPES","nat":"—","cat":"M 40–49","time":"03:19:16","sec":11956},{"pos":92,"bib":317,"name":"HUGH MCENEANEY","nat":"—","cat":"M 40–49","time":"03:19:43","sec":11983},{"pos":93,"bib":475,"name":"HOLLY TODD","nat":"—","cat":"W 20–39","time":"03:19:50","sec":11990},{"pos":94,"bib":500,"name":"BRYCE WARNER","nat":"—","cat":"M 20–39","time":"03:19:50","sec":11990},{"pos":95,"bib":476,"name":"CARMEL TOLHURST","nat":"—","cat":"W 20–39","time":"03:20:11","sec":12011},{"pos":96,"bib":314,"name":"KEN MCDONALD","nat":"—","cat":"M 20–39","time":"03:20:13","sec":12013},{"pos":97,"bib":548,"name":"MATTHEW ARNOLD","nat":"—","cat":"M 20–39","time":"03:20:24","sec":12024},{"pos":98,"bib":552,"name":"ANDREW CAVE","nat":"—","cat":"M 20–39","time":"03:20:47","sec":12047},{"pos":99,"bib":60,"name":"JAMES BRENT","nat":"—","cat":"M 20–39","time":"03:21:13","sec":12073},{"pos":100,"bib":251,"name":"ANTHONY KANE","nat":"—","cat":"M 40–49","time":"03:21:17","sec":12077},{"pos":101,"bib":267,"name":"SUZY KOFOED","nat":"—","cat":"W 20–39","time":"03:21:34","sec":12094},{"pos":102,"bib":279,"name":"SCOTT LEWIS","nat":"—","cat":"M 20–39","time":"03:21:34","sec":12094},{"pos":103,"bib":582,"name":"HINANO ANDREWS","nat":"—","cat":"W 20–39","time":"03:22:12","sec":12132},{"pos":104,"bib":225,"name":"GRAEME HENDERSON","nat":"—","cat":"M 40–49","time":"03:22:19","sec":12139},{"pos":105,"bib":300,"name":"SIMON MAISTER","nat":"—","cat":"M 20–39","time":"03:22:21","sec":12141},{"pos":106,"bib":35,"name":"JEREMY BATES","nat":"—","cat":"M 20–39","time":"03:22:44","sec":12164},{"pos":107,"bib":330,"name":"SARAH MCLEOD","nat":"—","cat":"W 40–49","time":"03:22:56","sec":12176},{"pos":108,"bib":386,"name":"CHRIS PENNELL","nat":"—","cat":"M 40–49","time":"03:23:04","sec":12184},{"pos":109,"bib":347,"name":"IAN MORGAN","nat":"—","cat":"M 40–49","time":"03:23:08","sec":12188},{"pos":110,"bib":87,"name":"GEORGY CHERIAN","nat":"—","cat":"M 20–39","time":"03:24:12","sec":12252},{"pos":111,"bib":124,"name":"VINCE DALBY","nat":"—","cat":"M 50–59","time":"03:24:26","sec":12266},{"pos":112,"bib":197,"name":"SAM GUO","nat":"—","cat":"M 20–39","time":"03:24:29","sec":12269},{"pos":113,"bib":361,"name":"MICHAEL NATHAN","nat":"—","cat":"M 20–39","time":"03:24:35","sec":12275},{"pos":114,"bib":215,"name":"GRANT HASTIE","nat":"—","cat":"M 50–59","time":"03:24:35","sec":12275},{"pos":115,"bib":133,"name":"BARRY DEWAR","nat":"—","cat":"M 60–69","time":"03:24:42","sec":12282},{"pos":116,"bib":368,"name":"JASON NUTBROWN","nat":"—","cat":"M 20–39","time":"03:24:58","sec":12298},{"pos":117,"bib":138,"name":"GAVIN DONNER","nat":"—","cat":"M 40–49","time":"03:25:29","sec":12329},{"pos":118,"bib":93,"name":"MEG CHRISTIE","nat":"—","cat":"W 50–59","time":"03:25:59","sec":12359},{"pos":119,"bib":496,"name":"ANDREW WAKEFIELD","nat":"—","cat":"M 20–39","time":"03:26:08","sec":12368},{"pos":120,"bib":9,"name":"CLARK AMBROSE","nat":"—","cat":"M 40–49","time":"03:26:32","sec":12392},{"pos":121,"bib":57,"name":"RICHARD BOYCE","nat":"—","cat":"M 40–49","time":"03:26:37","sec":12397},{"pos":122,"bib":304,"name":"JANA MARUSAKOVA","nat":"—","cat":"W 40–49","time":"03:27:06","sec":12426},{"pos":123,"bib":294,"name":"MODESTO JR. MADALANG","nat":"—","cat":"M 40–49","time":"03:27:15","sec":12435},{"pos":124,"bib":335,"name":"BRETT MCPHEDRAN","nat":"—","cat":"M 20–39","time":"03:27:31","sec":12451},{"pos":125,"bib":205,"name":"ANGELA HANCOCK","nat":"—","cat":"W 20–39","time":"03:27:43","sec":12463},{"pos":126,"bib":333,"name":"CHARLIE MCNALLY","nat":"—","cat":"M 50–59","time":"03:27:44","sec":12464},{"pos":127,"bib":362,"name":"PHILIP NEVELL","nat":"—","cat":"M 40–49","time":"03:28:04","sec":12484},{"pos":128,"bib":311,"name":"MICHAEL MCCORKINDALE","nat":"—","cat":"M 20–39","time":"03:28:54","sec":12534},{"pos":129,"bib":92,"name":"NEIL CHRISTIAN","nat":"—","cat":"M 40–49","time":"03:29:05","sec":12545},{"pos":130,"bib":293,"name":"JOHN MACDONALD","nat":"—","cat":"M 40–49","time":"03:29:08","sec":12548},{"pos":131,"bib":117,"name":"DAVE COX","nat":"—","cat":"M 40–49","time":"03:29:26","sec":12566},{"pos":132,"bib":234,"name":"MICHAEL HUIZINGA","nat":"—","cat":"M 20–39","time":"03:29:27","sec":12567},{"pos":133,"bib":170,"name":"OWEN FOSTER","nat":"—","cat":"M 40–49","time":"03:29:50","sec":12590},{"pos":134,"bib":332,"name":"TIM MCLEOD","nat":"—","cat":"M 50–59","time":"03:30:24","sec":12624},{"pos":135,"bib":410,"name":"PETER RICHARDS","nat":"—","cat":"M 50–59","time":"03:30:33","sec":12633},{"pos":136,"bib":244,"name":"ARNE JACOBSEN","nat":"—","cat":"M 40–49","time":"03:30:34","sec":12634},{"pos":137,"bib":406,"name":"JO REID","nat":"—","cat":"W 20–39","time":"03:30:35","sec":12635},{"pos":138,"bib":565,"name":"JOHN COSSENS","nat":"—","cat":"M 50–59","time":"03:30:41","sec":12641},{"pos":139,"bib":247,"name":"PEDRO JOHNSTON","nat":"—","cat":"M 20–39","time":"03:30:44","sec":12644},{"pos":140,"bib":161,"name":"SARAH FIEN","nat":"—","cat":"W 40–49","time":"03:30:45","sec":12645},{"pos":141,"bib":121,"name":"EMMA CRICHTON","nat":"—","cat":"W 40–49","time":"03:30:45","sec":12645},{"pos":142,"bib":202,"name":"PETER HALL","nat":"—","cat":"M 40–49","time":"03:31:04","sec":12664},{"pos":143,"bib":563,"name":"MARK DICKSON","nat":"—","cat":"M 40–49","time":"03:31:19","sec":12679},{"pos":144,"bib":101,"name":"CARWYN COCKERILL","nat":"—","cat":"M 40–49","time":"03:31:30","sec":12690},{"pos":145,"bib":208,"name":"MIKE HANSON","nat":"—","cat":"M 40–49","time":"03:31:46","sec":12706},{"pos":146,"bib":328,"name":"KRIS MCLEISH","nat":"—","cat":"M 20–39","time":"03:32:06","sec":12726},{"pos":147,"bib":204,"name":"BENJAMIN HAMMOND","nat":"—","cat":"M 20–39","time":"03:33:02","sec":12782},{"pos":148,"bib":530,"name":"MICHAEL WRIGLEY","nat":"—","cat":"M 40–49","time":"03:33:40","sec":12820},{"pos":149,"bib":387,"name":"ROBYN PERKINS","nat":"—","cat":"W 50–59","time":"03:33:41","sec":12821},{"pos":150,"bib":474,"name":"CARL TINKER","nat":"—","cat":"M 40–49","time":"03:34:18","sec":12858},{"pos":151,"bib":80,"name":"DAVID CARY","nat":"—","cat":"M 50–59","time":"03:34:49","sec":12889},{"pos":152,"bib":425,"name":"HANNAH SCOLLAN","nat":"—","cat":"W 20–39","time":"03:35:00","sec":12900},{"pos":153,"bib":462,"name":"ANDY TAYLOR","nat":"—","cat":"M 40–49","time":"03:35:37","sec":12937},{"pos":154,"bib":463,"name":"LISA TAYLOR","nat":"—","cat":"W 40–49","time":"03:36:19","sec":12979},{"pos":155,"bib":352,"name":"EMILY MORRIS","nat":"—","cat":"W 20–39","time":"03:37:04","sec":13024},{"pos":156,"bib":181,"name":"GEOFF GILFEDDER","nat":"—","cat":"M 40–49","time":"03:37:20","sec":13040},{"pos":157,"bib":210,"name":"PAUL HARFORD","nat":"—","cat":"M 40–49","time":"03:37:25","sec":13045},{"pos":158,"bib":110,"name":"PETER CONLEY","nat":"—","cat":"M 40–49","time":"03:37:26","sec":13046},{"pos":159,"bib":579,"name":"GUS HEWITT","nat":"—","cat":"M 20–39","time":"03:37:30","sec":13050},{"pos":160,"bib":303,"name":"CHRISTIAN MARTIN","nat":"—","cat":"M 20–39","time":"03:37:50","sec":13070},{"pos":161,"bib":506,"name":"NICOLA WHALLEY","nat":"—","cat":"W 40–49","time":"03:38:26","sec":13106},{"pos":162,"bib":104,"name":"PETER CODYRE","nat":"—","cat":"M 20–39","time":"03:38:52","sec":13132},{"pos":163,"bib":19,"name":"BRENDAN ANSTISS","nat":"—","cat":"M 40–49","time":"03:38:58","sec":13138},{"pos":164,"bib":535,"name":"RICHARD YOUNG","nat":"—","cat":"M 50–59","time":"03:39:03","sec":13143},{"pos":165,"bib":252,"name":"KIKO TAKAKO KATSUMOTO","nat":"—","cat":"W 40–49","time":"03:39:18","sec":13158},{"pos":166,"bib":154,"name":"BRIAN ELLWOOD","nat":"—","cat":"M 40–49","time":"03:39:48","sec":13188},{"pos":167,"bib":248,"name":"XANTHE JOHNSTON","nat":"—","cat":"W 20–39","time":"03:40:32","sec":13232},{"pos":168,"bib":451,"name":"PHILIP STEWART","nat":"—","cat":"M 20–39","time":"03:40:34","sec":13234},{"pos":169,"bib":79,"name":"CLARKE CARSON","nat":"—","cat":"M 20–39","time":"03:40:52","sec":13252},{"pos":170,"bib":36,"name":"ANNIE BATHURST","nat":"—","cat":"W 40–49","time":"03:41:44","sec":13304},{"pos":171,"bib":396,"name":"SANDRA POLAND","nat":"—","cat":"W 40–49","time":"03:41:57","sec":13317},{"pos":172,"bib":207,"name":"MICHELLE HANSEN","nat":"—","cat":"W 20–39","time":"03:41:59","sec":13319},{"pos":173,"bib":50,"name":"CAM PRESTON","nat":"—","cat":"M 20–39","time":"03:42:03","sec":13323},{"pos":174,"bib":320,"name":"NICK MCINTOSH","nat":"—","cat":"M 20–39","time":"03:42:06","sec":13326},{"pos":175,"bib":137,"name":"KIERAN DOLAN","nat":"—","cat":"M 40–49","time":"03:42:08","sec":13328},{"pos":176,"bib":14,"name":"KIM ANDERSON-HADLEY","nat":"—","cat":"W 40–49","time":"03:42:13","sec":13333},{"pos":177,"bib":269,"name":"OLIVIER LACOUA","nat":"—","cat":"M 40–49","time":"03:42:14","sec":13334},{"pos":178,"bib":458,"name":"TAKESHI TAKANE","nat":"—","cat":"M 40–49","time":"03:42:31","sec":13351},{"pos":179,"bib":443,"name":"SACHIKO SPEARS","nat":"—","cat":"W 50–59","time":"03:43:15","sec":13395},{"pos":180,"bib":477,"name":"XEVIER TONACAO","nat":"—","cat":"M 20–39","time":"03:43:55","sec":13435},{"pos":181,"bib":327,"name":"GLENN MCLAUGHLIN","nat":"—","cat":"M 40–49","time":"03:44:09","sec":13449},{"pos":182,"bib":16,"name":"MEGAN ANDREWS","nat":"—","cat":"W 40–49","time":"03:44:24","sec":13464},{"pos":183,"bib":22,"name":"GRANT ARMESSEN","nat":"—","cat":"M 20–39","time":"03:44:28","sec":13468},{"pos":184,"bib":490,"name":"RICHARD VAN WYNBERGEN","nat":"—","cat":"M 50–59","time":"03:44:54","sec":13494},{"pos":185,"bib":246,"name":"NICK JOHNSON","nat":"—","cat":"M 40–49","time":"03:44:59","sec":13499},{"pos":186,"bib":157,"name":"ANTONY FAIRBANKS","nat":"—","cat":"M 40–49","time":"03:45:00","sec":13500},{"pos":187,"bib":417,"name":"LUKE ROBERTSON","nat":"—","cat":"M 20–39","time":"03:45:05","sec":13505},{"pos":188,"bib":136,"name":"ZOE KIRKMAN","nat":"—","cat":"W 20–39","time":"03:45:10","sec":13510},{"pos":189,"bib":587,"name":"WILLIAM ADLAM","nat":"—","cat":"M 20–39","time":"03:46:12","sec":13572},{"pos":190,"bib":329,"name":"JAMES MCLELLAND","nat":"—","cat":"M 20–39","time":"03:46:19","sec":13579},{"pos":191,"bib":71,"name":"NICHOLAS BUCKLEY","nat":"—","cat":"M 20–39","time":"03:46:33","sec":13593},{"pos":192,"bib":504,"name":"MIKE WEBB","nat":"—","cat":"M 40–49","time":"03:46:40","sec":13600},{"pos":193,"bib":278,"name":"NICK LEITH","nat":"—","cat":"M 20–39","time":"03:46:56","sec":13616},{"pos":194,"bib":40,"name":"ANDREW BEASLEY","nat":"—","cat":"M 40–49","time":"03:46:58","sec":13618},{"pos":195,"bib":525,"name":"BRUCE WOODS","nat":"—","cat":"M 60–69","time":"03:47:01","sec":13621},{"pos":196,"bib":143,"name":"MARK DOWD","nat":"—","cat":"M 40–49","time":"03:47:06","sec":13626},{"pos":197,"bib":467,"name":"BLAIR TEMPLETON","nat":"—","cat":"M 20–39","time":"03:47:08","sec":13628},{"pos":198,"bib":493,"name":"MICHAEL VESTY","nat":"—","cat":"M 20–39","time":"03:47:30","sec":13650},{"pos":199,"bib":349,"name":"CRAIG MORICE","nat":"—","cat":"M 20–39","time":"03:47:31","sec":13651},{"pos":200,"bib":364,"name":"JENNIE NICHOLSON","nat":"—","cat":"W 40–49","time":"03:47:42","sec":13662},{"pos":201,"bib":196,"name":"SARAH GRIMES","nat":"—","cat":"W 40–49","time":"03:48:36","sec":13716},{"pos":202,"bib":382,"name":"MELANIE PATTERSON","nat":"—","cat":"W 40–49","time":"03:48:38","sec":13718},{"pos":203,"bib":173,"name":"FINLAY FRASER MILNE","nat":"—","cat":"M 20–39","time":"03:49:03","sec":13743},{"pos":204,"bib":7,"name":"DEREK ALSTON","nat":"—","cat":"M 40–49","time":"03:49:06","sec":13746},{"pos":205,"bib":394,"name":"MATTHEW PETTERSSON","nat":"—","cat":"M 20–39","time":"03:49:38","sec":13778},{"pos":206,"bib":31,"name":"DAVE BALDRY","nat":"—","cat":"M 50–59","time":"03:49:59","sec":13799},{"pos":207,"bib":141,"name":"KAREN DORSEY","nat":"—","cat":"W 40–49","time":"03:50:01","sec":13801},{"pos":208,"bib":195,"name":"JAMES GRIFFITH","nat":"—","cat":"M 20–39","time":"03:50:04","sec":13804},{"pos":209,"bib":573,"name":"CONNOR STEAD","nat":"—","cat":"M 20–39","time":"03:50:14","sec":13814},{"pos":210,"bib":466,"name":"JO TEBBUTT","nat":"—","cat":"W 40–49","time":"03:50:23","sec":13823},{"pos":211,"bib":221,"name":"PATRICIA HAYDEN-PAYNE","nat":"—","cat":"W 50–59","time":"03:50:42","sec":13842},{"pos":212,"bib":355,"name":"WILL MORRISH","nat":"—","cat":"M 50–59","time":"03:50:49","sec":13849},{"pos":213,"bib":341,"name":"BRENDAN MOLLOY","nat":"—","cat":"M 40–49","time":"03:50:55","sec":13855},{"pos":214,"bib":148,"name":"DAVE EATON","nat":"—","cat":"M 60–69","time":"03:51:05","sec":13865},{"pos":215,"bib":217,"name":"PETE HAWARD","nat":"—","cat":"M 20–39","time":"03:51:06","sec":13866},{"pos":216,"bib":419,"name":"TREVOR ROBINSON","nat":"—","cat":"M 50–59","time":"03:51:10","sec":13870},{"pos":217,"bib":403,"name":"CATHERINE QUIN","nat":"—","cat":"W 40–49","time":"03:51:14","sec":13874},{"pos":218,"bib":312,"name":"STU MCCORMACK","nat":"—","cat":"M 60–69","time":"03:51:24","sec":13884},{"pos":219,"bib":411,"name":"BILL RICHARDSON","nat":"—","cat":"M 60–69","time":"03:51:29","sec":13889},{"pos":220,"bib":509,"name":"HARRY WHITE","nat":"—","cat":"M 20–39","time":"03:51:40","sec":13900},{"pos":221,"bib":480,"name":"HIROSHI TOYOSHIMA","nat":"—","cat":"M 40–49","time":"03:51:43","sec":13903},{"pos":222,"bib":381,"name":"VARSHA PATEL","nat":"—","cat":"W 40–49","time":"03:51:46","sec":13906},{"pos":223,"bib":521,"name":"DEAN WILSON","nat":"—","cat":"M 40–49","time":"03:51:54","sec":13914},{"pos":224,"bib":185,"name":"KATHERINE GOOM","nat":"—","cat":"W 40–49","time":"03:51:55","sec":13915},{"pos":225,"bib":222,"name":"NICOLA HAYWOOD","nat":"—","cat":"W 20–39","time":"03:51:58","sec":13918},{"pos":226,"bib":541,"name":"MILLIE MCKELVIE","nat":"—","cat":"W 20–39","time":"03:52:01","sec":13921},{"pos":227,"bib":94,"name":"MARTIN CHURCHER","nat":"—","cat":"M 20–39","time":"03:52:14","sec":13934},{"pos":228,"bib":274,"name":"ADRIAN LAVE","nat":"—","cat":"M 40–49","time":"03:52:30","sec":13950},{"pos":229,"bib":231,"name":"GARETH HOLEBROOK","nat":"—","cat":"M 40–49","time":"03:52:31","sec":13951},{"pos":230,"bib":76,"name":"VICKY CALLINICOS","nat":"—","cat":"W 20–39","time":"03:52:38","sec":13958},{"pos":231,"bib":481,"name":"JENNA TRELEASE","nat":"—","cat":"W 20–39","time":"03:53:20","sec":14000},{"pos":232,"bib":434,"name":"BRAD SIMONS","nat":"—","cat":"M 20–39","time":"03:53:22","sec":14002},{"pos":233,"bib":531,"name":"MARK WYBOURNE","nat":"—","cat":"M 50–59","time":"03:54:07","sec":14047},{"pos":234,"bib":85,"name":"NICKI CHEN","nat":"—","cat":"M 20–39","time":"03:54:15","sec":14055},{"pos":235,"bib":70,"name":"HENRY BUCKINGHAM","nat":"—","cat":"M 20–39","time":"03:54:30","sec":14070},{"pos":236,"bib":418,"name":"PETE ROBINSON","nat":"—","cat":"M 40–49","time":"03:54:47","sec":14087},{"pos":237,"bib":128,"name":"JOHNNY DAVIES","nat":"—","cat":"M 20–39","time":"03:55:04","sec":14104},{"pos":238,"bib":289,"name":"YOSHIKO LOWRY","nat":"—","cat":"W 40–49","time":"03:55:28","sec":14128},{"pos":239,"bib":514,"name":"HENRY WILKINSON","nat":"—","cat":"M 20–39","time":"03:55:34","sec":14134},{"pos":240,"bib":209,"name":"MARK HARDING","nat":"—","cat":"M 20–39","time":"03:55:35","sec":14135},{"pos":241,"bib":180,"name":"ROBERT GILDER","nat":"—","cat":"M 20–39","time":"03:56:03","sec":14163},{"pos":242,"bib":432,"name":"ANDREW SHREEVE","nat":"—","cat":"M 40–49","time":"03:56:13","sec":14173},{"pos":243,"bib":223,"name":"MARGARET HAZELWOOD","nat":"—","cat":"W 60–69","time":"03:56:24","sec":14184},{"pos":244,"bib":167,"name":"HAYLEY FLETT","nat":"—","cat":"W 40–49","time":"03:56:38","sec":14198},{"pos":245,"bib":437,"name":"MARK SISSONS","nat":"—","cat":"M 20–39","time":"03:56:46","sec":14206},{"pos":246,"bib":469,"name":"JAMIE THOMSON","nat":"—","cat":"M 20–39","time":"03:56:50","sec":14210},{"pos":247,"bib":377,"name":"CRAIG PANNETT","nat":"—","cat":"M 40–49","time":"03:56:52","sec":14212},{"pos":248,"bib":2,"name":"DAVID ACKERMANN","nat":"—","cat":"M 20–39","time":"03:56:57","sec":14217},{"pos":249,"bib":321,"name":"HAMISH MCINTYRE","nat":"—","cat":"M 20–39","time":"03:56:59","sec":14219},{"pos":250,"bib":439,"name":"LISA SMITH","nat":"—","cat":"W 20–39","time":"03:57:11","sec":14231},{"pos":251,"bib":454,"name":"PETER STURGES","nat":"—","cat":"M 40–49","time":"03:57:22","sec":14242},{"pos":252,"bib":108,"name":"STEVEN CONDLIFFE","nat":"—","cat":"M 40–49","time":"03:57:24","sec":14244},{"pos":253,"bib":427,"name":"FRANCES SCRIMGEOUR","nat":"—","cat":"W 20–39","time":"03:57:30","sec":14250},{"pos":254,"bib":103,"name":"PETER CODY","nat":"—","cat":"M 20–39","time":"03:57:41","sec":14261},{"pos":255,"bib":526,"name":"ROB WOODS","nat":"—","cat":"M 40–49","time":"03:57:50","sec":14270},{"pos":256,"bib":218,"name":"CHRIS HAWKE","nat":"—","cat":"M 20–39","time":"03:58:13","sec":14293},{"pos":257,"bib":266,"name":"LEA KNOWLES","nat":"—","cat":"W 40–49","time":"03:58:17","sec":14297},{"pos":258,"bib":348,"name":"LAURA MORGAN","nat":"—","cat":"W 20–39","time":"03:58:28","sec":14308},{"pos":259,"bib":532,"name":"PHILIP XIE","nat":"—","cat":"M 20–39","time":"03:58:35","sec":14315},{"pos":260,"bib":235,"name":"JENNY HUNG","nat":"—","cat":"W 20–39","time":"03:58:37","sec":14317},{"pos":261,"bib":407,"name":"JESSIE REYES","nat":"—","cat":"M 40–49","time":"03:58:40","sec":14320},{"pos":262,"bib":569,"name":"CHRIS WRIGHT","nat":"—","cat":"M 40–49","time":"03:58:56","sec":14336},{"pos":263,"bib":501,"name":"BRADYN WATSON","nat":"—","cat":"M 20–39","time":"03:59:00","sec":14340},{"pos":264,"bib":49,"name":"PAULETTE BIRCHFIELD","nat":"—","cat":"W 40–49","time":"03:59:08","sec":14348},{"pos":265,"bib":107,"name":"SHARLEEN COLLINS","nat":"—","cat":"W 40–49","time":"03:59:28","sec":14368},{"pos":266,"bib":371,"name":"TONY O'KEEFFE","nat":"—","cat":"M 20–39","time":"03:59:34","sec":14374},{"pos":267,"bib":153,"name":"CLAIRE ELLIOTT","nat":"—","cat":"W 20–39","time":"03:59:55","sec":14395},{"pos":268,"bib":163,"name":"LUCAS FIRTH","nat":"—","cat":"M 20–39","time":"03:59:59","sec":14399},{"pos":269,"bib":465,"name":"PETER TAYLOR","nat":"—","cat":"M 20–39","time":"04:00:12","sec":14412},{"pos":270,"bib":519,"name":"BLAIR WILLIAMSON","nat":"—","cat":"M 20–39","time":"04:00:17","sec":14417},{"pos":271,"bib":233,"name":"PETER HUGHES","nat":"—","cat":"M 60–69","time":"04:00:38","sec":14438},{"pos":272,"bib":337,"name":"ISIS METCALFE","nat":"—","cat":"W 20–39","time":"04:00:48","sec":14448},{"pos":273,"bib":67,"name":"JORDAN BUCHANAN","nat":"—","cat":"M 20–39","time":"04:01:08","sec":14468},{"pos":274,"bib":38,"name":"JOSIAH BEACH","nat":"—","cat":"M 20–39","time":"04:01:09","sec":14469},{"pos":275,"bib":497,"name":"HAMISH WALL","nat":"—","cat":"M 20–39","time":"04:01:18","sec":14478},{"pos":276,"bib":99,"name":"MEYRICK CLAYDEN","nat":"—","cat":"M 40–49","time":"04:01:23","sec":14483},{"pos":277,"bib":297,"name":"NICK MAHONEY","nat":"—","cat":"M 20–39","time":"04:01:26","sec":14486},{"pos":278,"bib":546,"name":"WAYNE CURREY","nat":"—","cat":"M 40–49","time":"04:01:28","sec":14488},{"pos":279,"bib":306,"name":"HAMISH MASON","nat":"—","cat":"M 40–49","time":"04:01:34","sec":14494},{"pos":280,"bib":527,"name":"BEN WORTELBOER","nat":"—","cat":"M 20–39","time":"04:01:48","sec":14508},{"pos":281,"bib":588,"name":"DANIEL COLLINS","nat":"—","cat":"M 20–39","time":"04:01:50","sec":14510},{"pos":282,"bib":63,"name":"MICHAEL BROWN","nat":"—","cat":"M 20–39","time":"04:02:04","sec":14524},{"pos":283,"bib":307,"name":"DAVID MASSEY","nat":"—","cat":"M 40–49","time":"04:02:07","sec":14527},{"pos":284,"bib":473,"name":"GRAEME TINDALL","nat":"—","cat":"M 40–49","time":"04:02:10","sec":14530},{"pos":285,"bib":508,"name":"CHRISTOPHER WHITE","nat":"—","cat":"M 20–39","time":"04:02:30","sec":14550},{"pos":286,"bib":429,"name":"JULIANNE SHARP","nat":"—","cat":"W 40–49","time":"04:02:47","sec":14567},{"pos":287,"bib":182,"name":"CHAD GILLESPIE","nat":"—","cat":"M 40–49","time":"04:03:14","sec":14594},{"pos":288,"bib":237,"name":"WILLIAM HUNTER","nat":"—","cat":"M 50–59","time":"04:03:45","sec":14625},{"pos":289,"bib":146,"name":"STEVEN DUNN","nat":"—","cat":"M 40–49","time":"04:03:46","sec":14626},{"pos":290,"bib":517,"name":"LEANNA WILLIAMS","nat":"—","cat":"W 20–39","time":"04:03:47","sec":14627},{"pos":291,"bib":422,"name":"STEPHANIE RUMBLE","nat":"—","cat":"W 40–49","time":"04:03:48","sec":14628},{"pos":292,"bib":431,"name":"ROBERT SHELTON","nat":"—","cat":"M 20–39","time":"04:03:55","sec":14635},{"pos":293,"bib":23,"name":"PETER ARMSTRONG","nat":"—","cat":"M 20–39","time":"04:04:00","sec":14640},{"pos":294,"bib":3,"name":"ROBERT AIKMAN","nat":"—","cat":"M 50–59","time":"04:04:09","sec":14649},{"pos":295,"bib":556,"name":"SUE MELTZER","nat":"—","cat":"W 60–69","time":"04:04:17","sec":14657},{"pos":296,"bib":292,"name":"ERIC JOHN LUNA","nat":"—","cat":"M 20–39","time":"04:04:28","sec":14668},{"pos":297,"bib":342,"name":"TOM MONAGHAN","nat":"—","cat":"M 20–39","time":"04:04:28","sec":14668},{"pos":298,"bib":190,"name":"SHEREE GRANT","nat":"—","cat":"W 40–49","time":"04:04:31","sec":14671},{"pos":299,"bib":135,"name":"JONATHAN DILLON","nat":"—","cat":"M 40–49","time":"04:04:46","sec":14686},{"pos":300,"bib":134,"name":"AARTI DIAR","nat":"—","cat":"W 20–39","time":"04:05:07","sec":14707},{"pos":301,"bib":302,"name":"CLAIRE MARTIN","nat":"—","cat":"W 40–49","time":"04:05:07","sec":14707},{"pos":302,"bib":373,"name":"PHIL OWEN","nat":"—","cat":"M 20–39","time":"04:05:16","sec":14716},{"pos":303,"bib":452,"name":"ANGELA STOCKDALE","nat":"—","cat":"W 20–39","time":"04:06:13","sec":14773},{"pos":304,"bib":442,"name":"EDWARD SPARROW","nat":"—","cat":"M 40–49","time":"04:06:15","sec":14775},{"pos":305,"bib":578,"name":"BERNIE O'FAGAN","nat":"—","cat":"M 50–59","time":"04:06:18","sec":14778},{"pos":306,"bib":494,"name":"NATHAN VINEY","nat":"—","cat":"M 20–39","time":"04:06:29","sec":14789},{"pos":307,"bib":453,"name":"ROBERT STOWELL","nat":"—","cat":"M 20–39","time":"04:06:35","sec":14795},{"pos":308,"bib":8,"name":"SHIN AMANO","nat":"—","cat":"M 50–59","time":"04:06:44","sec":14804},{"pos":309,"bib":193,"name":"SIMON GREIG","nat":"—","cat":"M 50–59","time":"04:06:56","sec":14816},{"pos":310,"bib":241,"name":"ELIZABETH IRELAND","nat":"—","cat":"W 20–39","time":"04:07:09","sec":14829},{"pos":311,"bib":539,"name":"MICHAEL WEIR","nat":"—","cat":"M 40–49","time":"04:07:55","sec":14875},{"pos":312,"bib":557,"name":"MEGAN BLAKELY","nat":"—","cat":"W 20–39","time":"04:08:24","sec":14904},{"pos":313,"bib":512,"name":"TANSY WIGLEY","nat":"—","cat":"W 20–39","time":"04:08:50","sec":14930},{"pos":314,"bib":42,"name":"JAMIE BELL","nat":"—","cat":"M 20–39","time":"04:08:52","sec":14932},{"pos":315,"bib":428,"name":"CARLO SERRANO","nat":"—","cat":"M 20–39","time":"04:09:10","sec":14950},{"pos":316,"bib":69,"name":"PAMELA BUCHWALD","nat":"—","cat":"W 20–39","time":"04:09:41","sec":14981},{"pos":317,"bib":378,"name":"JAMES PARK","nat":"—","cat":"M 50–59","time":"04:09:54","sec":14994},{"pos":318,"bib":20,"name":"RICHARD ANTHONY","nat":"—","cat":"M 20–39","time":"04:10:03","sec":15003},{"pos":319,"bib":323,"name":"DEAN MCKENZIE","nat":"—","cat":"M 40–49","time":"04:10:28","sec":15028},{"pos":320,"bib":334,"name":"ROB MCNEUR","nat":"—","cat":"M 50–59","time":"04:10:29","sec":15029},{"pos":321,"bib":379,"name":"ROBBIE PARK","nat":"—","cat":"M 20–39","time":"04:10:38","sec":15038},{"pos":322,"bib":280,"name":"SHENG YU LIN","nat":"—","cat":"M 20–39","time":"04:10:39","sec":15039},{"pos":323,"bib":68,"name":"FREDRIK BUCHWALD","nat":"—","cat":"M 40–49","time":"04:12:15","sec":15135},{"pos":324,"bib":126,"name":"SILVER DALY","nat":"—","cat":"M 20–39","time":"04:12:18","sec":15138},{"pos":325,"bib":140,"name":"ANDRAS THOMAS DOOLITTLE","nat":"—","cat":"M 20–39","time":"04:12:35","sec":15155},{"pos":326,"bib":33,"name":"GEORGE BARRY","nat":"—","cat":"M 20–39","time":"04:12:38","sec":15158},{"pos":327,"bib":127,"name":"PETER DAVIDSON","nat":"—","cat":"M 60–69","time":"04:12:41","sec":15161},{"pos":328,"bib":404,"name":"KIRSTIN RAMSAY","nat":"—","cat":"W 20–39","time":"04:12:41","sec":15161},{"pos":329,"bib":32,"name":"PAULETTE BALDRY","nat":"—","cat":"W 50–59","time":"04:12:43","sec":15163},{"pos":330,"bib":34,"name":"EMILY BARTON","nat":"—","cat":"W 20–39","time":"04:13:04","sec":15184},{"pos":331,"bib":558,"name":"WATTIE MORTIMER","nat":"—","cat":"M 40–49","time":"04:13:15","sec":15195},{"pos":332,"bib":560,"name":"REBECCA LADBROOK","nat":"—","cat":"W 20–39","time":"04:13:42","sec":15222},{"pos":333,"bib":199,"name":"ELIZABETH HADFIELD","nat":"—","cat":"W 40–49","time":"04:13:43","sec":15223},{"pos":334,"bib":498,"name":"ROBIN WALLACE","nat":"—","cat":"M 20–39","time":"04:14:11","sec":15251},{"pos":335,"bib":82,"name":"CHRIS CHAMPION","nat":"—","cat":"M 20–39","time":"04:14:53","sec":15293},{"pos":336,"bib":10,"name":"ERROL AMYES","nat":"—","cat":"M 50–59","time":"04:14:56","sec":15296},{"pos":337,"bib":174,"name":"MARK FULLER","nat":"—","cat":"M 50–59","time":"04:14:57","sec":15297},{"pos":338,"bib":262,"name":"GRANT KIRTON","nat":"—","cat":"M 40–49","time":"04:15:04","sec":15304},{"pos":339,"bib":471,"name":"JULIA THORN","nat":"—","cat":"W 50–59","time":"04:15:09","sec":15309},{"pos":340,"bib":433,"name":"LEMI SI'ITIA","nat":"—","cat":"M 20–39","time":"04:15:16","sec":15316},{"pos":341,"bib":242,"name":"RICHARD JACK","nat":"—","cat":"M 40–49","time":"04:15:24","sec":15324},{"pos":342,"bib":315,"name":"PAUL MCDONALD","nat":"—","cat":"M 20–39","time":"04:15:28","sec":15328},{"pos":343,"bib":491,"name":"GAZ VAUGHAN","nat":"—","cat":"M 40–49","time":"04:16:25","sec":15385},{"pos":344,"bib":309,"name":"DONAL MAY","nat":"—","cat":"M 50–59","time":"04:16:50","sec":15410},{"pos":345,"bib":503,"name":"GILBERT WATSON","nat":"—","cat":"M 50–59","time":"04:17:28","sec":15448},{"pos":346,"bib":399,"name":"KIRI PRICE","nat":"—","cat":"W 40–49","time":"04:17:28","sec":15448},{"pos":347,"bib":73,"name":"DES BURKE","nat":"—","cat":"M 50–59","time":"04:17:37","sec":15457},{"pos":348,"bib":513,"name":"BEN WILKINSON","nat":"—","cat":"M 20–39","time":"04:17:48","sec":15468},{"pos":349,"bib":151,"name":"NATALIE EDWARDS","nat":"—","cat":"W 40–49","time":"04:17:51","sec":15471},{"pos":350,"bib":450,"name":"JAMES STEWART","nat":"—","cat":"M 20–39","time":"04:18:00","sec":15480},{"pos":351,"bib":41,"name":"EMILY BELL","nat":"—","cat":"W 20–39","time":"04:18:11","sec":15491},{"pos":352,"bib":270,"name":"JACOB LAMONT","nat":"—","cat":"M 40–49","time":"04:18:14","sec":15494},{"pos":353,"bib":253,"name":"DUSTIN KECK","nat":"—","cat":"M 40–49","time":"04:18:40","sec":15520},{"pos":354,"bib":415,"name":"REGAN RISING","nat":"—","cat":"W 20–39","time":"04:18:40","sec":15520},{"pos":355,"bib":449,"name":"DAVE STEWART","nat":"—","cat":"M 40–49","time":"04:19:14","sec":15554},{"pos":356,"bib":551,"name":"JONAS SEKULLA","nat":"—","cat":"M 20–39","time":"04:19:29","sec":15569},{"pos":357,"bib":370,"name":"STEVE OEHLEY","nat":"—","cat":"M 20–39","time":"04:19:35","sec":15575},{"pos":358,"bib":572,"name":"TRACEY MCLAUGHLIN","nat":"—","cat":"W 40–49","time":"04:19:46","sec":15586},{"pos":359,"bib":98,"name":"TONY CLARKE","nat":"—","cat":"M 50–59","time":"04:20:11","sec":15611},{"pos":360,"bib":226,"name":"CHRISTOPHER HENDRIKS","nat":"—","cat":"M 40–49","time":"04:20:28","sec":15628},{"pos":361,"bib":220,"name":"ATSUSHI HAYASAKA","nat":"—","cat":"M 50–59","time":"04:20:32","sec":15632},{"pos":362,"bib":44,"name":"KERRY BELLRINGER","nat":"—","cat":"M 20–39","time":"04:20:38","sec":15638},{"pos":363,"bib":229,"name":"KARIN HERBST","nat":"—","cat":"W 50–59","time":"04:21:41","sec":15701},{"pos":364,"bib":408,"name":"BECKY RICHARDS","nat":"—","cat":"W 20–39","time":"04:22:12","sec":15732},{"pos":365,"bib":118,"name":"LUISA COYLE","nat":"—","cat":"W 20–39","time":"04:22:15","sec":15735},{"pos":366,"bib":533,"name":"SIMON XIE","nat":"—","cat":"M 40–49","time":"04:22:18","sec":15738},{"pos":367,"bib":492,"name":"RUDI VERPLANCKE","nat":"—","cat":"M 40–49","time":"04:22:24","sec":15744},{"pos":368,"bib":213,"name":"STEVE HARRIS","nat":"—","cat":"M 20–39","time":"04:22:37","sec":15757},{"pos":369,"bib":301,"name":"CEDRIC DOMINIQUE MARIGOT","nat":"—","cat":"M 40–49","time":"04:22:41","sec":15761},{"pos":370,"bib":261,"name":"BOB DOBSON","nat":"—","cat":"W 20–39","time":"04:22:42","sec":15762},{"pos":371,"bib":571,"name":"ANDREW TIMMINS","nat":"—","cat":"M 20–39","time":"04:23:02","sec":15782},{"pos":372,"bib":78,"name":"OLIVER CAREY","nat":"—","cat":"M 20–39","time":"04:23:06","sec":15786},{"pos":373,"bib":488,"name":"EDDY VAN OOSTEN","nat":"—","cat":"M 20–39","time":"04:23:23","sec":15803},{"pos":374,"bib":296,"name":"JORDAN MAHER","nat":"—","cat":"M 20–39","time":"04:23:49","sec":15829},{"pos":375,"bib":324,"name":"RICHELE MCKENZIE","nat":"—","cat":"W 40–49","time":"04:23:51","sec":15831},{"pos":376,"bib":390,"name":"JENNIFER PERRY","nat":"—","cat":"W 40–49","time":"04:23:56","sec":15836},{"pos":377,"bib":189,"name":"STEPHEN GRAHAM","nat":"—","cat":"M 50–59","time":"04:24:03","sec":15843},{"pos":378,"bib":456,"name":"NICKY SWEETMAN","nat":"—","cat":"W 40–49","time":"04:24:16","sec":15856},{"pos":379,"bib":122,"name":"CATHERINE CUMPSTONE","nat":"—","cat":"W 20–39","time":"04:24:37","sec":15877},{"pos":380,"bib":176,"name":"HAZEL GEORGE","nat":"—","cat":"W 20–39","time":"04:24:56","sec":15896},{"pos":381,"bib":478,"name":"MARK TOOMER","nat":"—","cat":"M 50–59","time":"04:25:02","sec":15902},{"pos":382,"bib":522,"name":"RONA WILSON","nat":"—","cat":"W 20–39","time":"04:25:12","sec":15912},{"pos":383,"bib":559,"name":"NATALIE HOGG","nat":"—","cat":"W 20–39","time":"04:25:37","sec":15937},{"pos":384,"bib":363,"name":"WARWICK NICHOLS","nat":"—","cat":"M 20–39","time":"04:26:00","sec":15960},{"pos":385,"bib":409,"name":"NATASHA RICHARDS","nat":"—","cat":"W 20–39","time":"04:26:11","sec":15971},{"pos":386,"bib":346,"name":"SIMON MORAN","nat":"—","cat":"M 20–39","time":"04:26:32","sec":15992},{"pos":387,"bib":580,"name":"CHRIS BENNETT","nat":"—","cat":"M 40–49","time":"04:27:07","sec":16027},{"pos":388,"bib":43,"name":"RUTH BELLEW","nat":"—","cat":"W 60–69","time":"04:27:23","sec":16043},{"pos":389,"bib":547,"name":"ANDREW REDMOND","nat":"—","cat":"M 40–49","time":"04:27:39","sec":16059},{"pos":390,"bib":164,"name":"EMMA FISSENDEN","nat":"—","cat":"W 20–39","time":"04:27:49","sec":16069},{"pos":391,"bib":55,"name":"MATTHEW BONE","nat":"—","cat":"M 40–49","time":"04:27:51","sec":16071},{"pos":392,"bib":393,"name":"PATRICK PETHICA","nat":"—","cat":"M 20–39","time":"04:27:56","sec":16076},{"pos":393,"bib":192,"name":"PAUL GREENSLADE","nat":"—","cat":"M 40–49","time":"04:28:21","sec":16101},{"pos":394,"bib":109,"name":"CRAIG CONLAN","nat":"—","cat":"M 40–49","time":"04:28:33","sec":16113},{"pos":395,"bib":520,"name":"GREG WILLIAMSON","nat":"—","cat":"M 40–49","time":"04:28:37","sec":16117},{"pos":396,"bib":288,"name":"MARCUS LOWE","nat":"—","cat":"M 20–39","time":"04:28:50","sec":16130},{"pos":397,"bib":88,"name":"IAN CHIBNALL","nat":"—","cat":"M 50–59","time":"04:28:52","sec":16132},{"pos":398,"bib":412,"name":"KATHY RICHARDSON","nat":"—","cat":"W 40–49","time":"04:29:21","sec":16161},{"pos":399,"bib":100,"name":"JOHN CLEGHORN","nat":"—","cat":"M 50–59","time":"04:29:34","sec":16174},{"pos":400,"bib":383,"name":"DANA PAUL","nat":"—","cat":"W 20–39","time":"04:29:37","sec":16177},{"pos":401,"bib":479,"name":"ERIN TOPP","nat":"—","cat":"W 20–39","time":"04:29:48","sec":16188},{"pos":402,"bib":584,"name":"ALLARD REGAN","nat":"—","cat":"W 20–39","time":"04:30:24","sec":16224},{"pos":403,"bib":470,"name":"MICHALLA THOMSON","nat":"—","cat":"W 20–39","time":"04:30:54","sec":16254},{"pos":404,"bib":130,"name":"NICKY DENSEM","nat":"—","cat":"W 20–39","time":"04:31:01","sec":16261},{"pos":405,"bib":259,"name":"JESSIE KING","nat":"—","cat":"W 40–49","time":"04:31:10","sec":16270},{"pos":406,"bib":543,"name":"ZANE HAWKEN","nat":"—","cat":"M 20–39","time":"04:31:10","sec":16270},{"pos":407,"bib":120,"name":"DARRYL CRIBB","nat":"—","cat":"M 40–49","time":"04:31:53","sec":16313},{"pos":408,"bib":264,"name":"GEOFF. KNIGHT","nat":"—","cat":"M 40–49","time":"04:31:53","sec":16313},{"pos":409,"bib":27,"name":"JAVIER AVILA","nat":"—","cat":"M 20–39","time":"04:32:37","sec":16357},{"pos":410,"bib":263,"name":"KURT KJESTRUP","nat":"—","cat":"M 50–59","time":"04:33:18","sec":16398},{"pos":411,"bib":272,"name":"ADRIENNE JANE LANGFORD","nat":"—","cat":"W 20–39","time":"04:33:26","sec":16406},{"pos":412,"bib":46,"name":"WARREN BERNARD","nat":"—","cat":"M 20–39","time":"04:33:36","sec":16416},{"pos":413,"bib":168,"name":"DEEANE FLEWELLEN","nat":"—","cat":"W 20–39","time":"04:34:01","sec":16441},{"pos":414,"bib":83,"name":"MAN KEI CHAN","nat":"—","cat":"M 40–49","time":"04:34:17","sec":16457},{"pos":415,"bib":322,"name":"BRONWYN MCKEAGE","nat":"—","cat":"W 40–49","time":"04:34:27","sec":16467},{"pos":416,"bib":445,"name":"KILMENY STEPHENS","nat":"—","cat":"W 40–49","time":"04:35:07","sec":16507},{"pos":417,"bib":30,"name":"STEPHEN BAKER","nat":"—","cat":"M 50–59","time":"04:35:11","sec":16511},{"pos":418,"bib":65,"name":"SEAN BRUNNER","nat":"—","cat":"M 40–49","time":"04:35:26","sec":16526},{"pos":419,"bib":26,"name":"CHRIS AVERILL","nat":"—","cat":"M 50–59","time":"04:35:43","sec":16543},{"pos":420,"bib":21,"name":"JAANA ARAMOWICZ","nat":"—","cat":"W 40–49","time":"04:35:44","sec":16544},{"pos":421,"bib":507,"name":"RACHAEL WHALLEY","nat":"—","cat":"W 40–49","time":"04:36:14","sec":16574},{"pos":422,"bib":15,"name":"HEATHER ANDREWS","nat":"—","cat":"W 40–49","time":"04:36:55","sec":16615},{"pos":423,"bib":86,"name":"VIVIAN CHENG","nat":"—","cat":"W 20–39","time":"04:36:55","sec":16615},{"pos":424,"bib":119,"name":"BERNIE CRAVEN","nat":"—","cat":"M 50–59","time":"04:37:43","sec":16663},{"pos":425,"bib":284,"name":"JOSHUA LOGAN","nat":"—","cat":"M 20–39","time":"04:37:43","sec":16663},{"pos":426,"bib":265,"name":"GARRY KNIGHT","nat":"—","cat":"M 40–49","time":"04:37:51","sec":16671},{"pos":427,"bib":201,"name":"MORRIS HALL","nat":"—","cat":"M 60–69","time":"04:37:54","sec":16674},{"pos":428,"bib":162,"name":"KATHRYN FINN","nat":"—","cat":"W 20–39","time":"04:38:02","sec":16682},{"pos":429,"bib":230,"name":"IAN HOAD","nat":"—","cat":"M 60–69","time":"04:38:10","sec":16690},{"pos":430,"bib":268,"name":"NICOLAS KRUIZE","nat":"—","cat":"M 20–39","time":"04:38:10","sec":16690},{"pos":431,"bib":131,"name":"CLEO DEVANEY","nat":"—","cat":"W 40–49","time":"04:38:31","sec":16711},{"pos":432,"bib":436,"name":"LOUISE SISSONS","nat":"—","cat":"W 40–49","time":"04:38:35","sec":16715},{"pos":433,"bib":345,"name":"CRAIG MORA","nat":"—","cat":"M 40–49","time":"04:39:03","sec":16743},{"pos":434,"bib":515,"name":"BRON WILLIAMS","nat":"—","cat":"W 40–49","time":"04:39:32","sec":16772},{"pos":435,"bib":402,"name":"CHRISTOPHER PUTWAIN","nat":"—","cat":"M 50–59","time":"04:39:44","sec":16784},{"pos":436,"bib":58,"name":"GRANANTAN BOYLE","nat":"—","cat":"M 40–49","time":"04:39:58","sec":16798},{"pos":437,"bib":129,"name":"ALEC DAY","nat":"—","cat":"M 70–99","time":"04:40:35","sec":16835},{"pos":438,"bib":549,"name":"TRACY HICKMAN","nat":"—","cat":"W 40–49","time":"04:40:50","sec":16850},{"pos":439,"bib":5,"name":"SAM ALEXANDER","nat":"—","cat":"M 20–39","time":"04:41:18","sec":16878},{"pos":440,"bib":132,"name":"NELLY DE VRIES","nat":"—","cat":"W 50–59","time":"04:41:24","sec":16884},{"pos":441,"bib":188,"name":"MIKE GRAHAM","nat":"—","cat":"M 50–59","time":"04:41:40","sec":16900},{"pos":442,"bib":183,"name":"HANNAH GILLESPIE","nat":"—","cat":"W 20–39","time":"04:41:46","sec":16906},{"pos":443,"bib":385,"name":"LYNN PEACOCK","nat":"—","cat":"W 20–39","time":"04:42:26","sec":16946},{"pos":444,"bib":228,"name":"NAOMI HERBERT","nat":"—","cat":"W 20–39","time":"04:42:27","sec":16947},{"pos":445,"bib":499,"name":"CHLOE WARD-SMITH","nat":"—","cat":"W 20–39","time":"04:42:41","sec":16961},{"pos":446,"bib":158,"name":"JACQUELINE FAIRBRASS","nat":"—","cat":"W 40–49","time":"04:42:46","sec":16966},{"pos":447,"bib":483,"name":"MAURICE TUA","nat":"—","cat":"M 40–49","time":"04:43:30","sec":17010},{"pos":448,"bib":271,"name":"KEITH LANE","nat":"—","cat":"M 50–59","time":"04:43:58","sec":17038},{"pos":449,"bib":54,"name":"ALEXANDRE BOJILOVE","nat":"—","cat":"M 60–69","time":"04:44:21","sec":17061},{"pos":450,"bib":282,"name":"HEMA LOCHAN","nat":"—","cat":"W 20–39","time":"04:44:36","sec":17076},{"pos":451,"bib":214,"name":"LISA HARTNETT","nat":"—","cat":"W 40–49","time":"04:44:37","sec":17077},{"pos":452,"bib":369,"name":"LINDSAY OAKLEY","nat":"—","cat":"M 50–59","time":"04:44:50","sec":17090},{"pos":453,"bib":139,"name":"GARRY DONOGHUE","nat":"—","cat":"M 60–69","time":"04:45:21","sec":17121},{"pos":454,"bib":24,"name":"ROBERT ASHFORD","nat":"—","cat":"M 50–59","time":"04:45:41","sec":17141},{"pos":455,"bib":25,"name":"SARAH AUGUST","nat":"—","cat":"W 20–39","time":"04:46:04","sec":17164},{"pos":456,"bib":149,"name":"REBECCA EDGECOMBE","nat":"—","cat":"W 40–49","time":"04:46:25","sec":17185},{"pos":457,"bib":391,"name":"LIAM PERRY","nat":"—","cat":"M 20–39","time":"04:47:20","sec":17240},{"pos":458,"bib":191,"name":"ANGELA GRATTAN","nat":"—","cat":"W 60–69","time":"04:47:32","sec":17252},{"pos":459,"bib":544,"name":"LISA MCKENZIE","nat":"—","cat":"W 20–39","time":"04:48:37","sec":17317},{"pos":460,"bib":295,"name":"KEVIN MADDERN","nat":"—","cat":"M 50–59","time":"04:48:50","sec":17330},{"pos":461,"bib":51,"name":"DANIELLE BLACKIE","nat":"—","cat":"W 20–39","time":"04:49:11","sec":17351},{"pos":462,"bib":343,"name":"CARL MOODY","nat":"—","cat":"M 50–59","time":"04:49:20","sec":17360},{"pos":463,"bib":166,"name":"MARK FLAGG","nat":"—","cat":"M 40–49","time":"04:49:46","sec":17386},{"pos":464,"bib":236,"name":"JONNY HUNTER","nat":"—","cat":"M 20–39","time":"04:49:48","sec":17388},{"pos":465,"bib":561,"name":"GREGORY HARRIS","nat":"—","cat":"M 50–59","time":"04:49:59","sec":17399},{"pos":466,"bib":366,"name":"MODECAI NKHWAZI","nat":"—","cat":"M 20–39","time":"04:50:34","sec":17434},{"pos":467,"bib":487,"name":"FOSTER VAN GRUTING","nat":"—","cat":"M 50–59","time":"04:50:44","sec":17444},{"pos":468,"bib":426,"name":"JONATHAN SCOTT","nat":"—","cat":"M 20–39","time":"04:50:53","sec":17453},{"pos":469,"bib":459,"name":"KELLY TAN","nat":"—","cat":"W 20–39","time":"04:51:51","sec":17511},{"pos":470,"bib":285,"name":"KIM LOONG LOH","nat":"—","cat":"M 20–39","time":"04:51:58","sec":17518},{"pos":471,"bib":310,"name":"DAVID MAYALL","nat":"—","cat":"M 20–39","time":"04:54:11","sec":17651},{"pos":472,"bib":89,"name":"COLIN CHIN","nat":"—","cat":"M 50–59","time":"04:54:30","sec":17670},{"pos":473,"bib":446,"name":"ED STEVENS","nat":"—","cat":"M 60–69","time":"04:54:57","sec":17697},{"pos":474,"bib":62,"name":"KATHRYN BROWN","nat":"—","cat":"W 20–39","time":"04:56:39","sec":17799},{"pos":475,"bib":464,"name":"MIKE TAYLOR","nat":"—","cat":"M 40–49","time":"04:57:18","sec":17838},{"pos":476,"bib":576,"name":"DAVID TUIA","nat":"—","cat":"M 40–49","time":"04:57:53","sec":17873},{"pos":477,"bib":283,"name":"SARAH LOCKYER","nat":"—","cat":"W 40–49","time":"04:59:14","sec":17954},{"pos":478,"bib":206,"name":"HUGO HANDYSIDE","nat":"—","cat":"M 20–39","time":"04:59:20","sec":17960},{"pos":479,"bib":84,"name":"SARA CHAPMAN","nat":"—","cat":"W 40–49","time":"04:59:21","sec":17961},{"pos":480,"bib":545,"name":"SIMON MILLER","nat":"—","cat":"M 20–39","time":"04:59:21","sec":17961},{"pos":481,"bib":160,"name":"DEBRA FENTON","nat":"—","cat":"W 50–59","time":"05:00:46","sec":18046},{"pos":482,"bib":287,"name":"RACHAEL LOVELOCK","nat":"—","cat":"W 20–39","time":"05:01:49","sec":18109},{"pos":483,"bib":566,"name":"DUNCAN WOODS","nat":"—","cat":"M 40–49","time":"05:02:00","sec":18120},{"pos":484,"bib":389,"name":"CRAIG PERRY","nat":"—","cat":"M 40–49","time":"05:02:01","sec":18121},{"pos":485,"bib":574,"name":"ALEXANDER GEE","nat":"—","cat":"M 20–39","time":"05:02:30","sec":18150},{"pos":486,"bib":405,"name":"GARY REGTIEN","nat":"—","cat":"M 70–99","time":"05:03:42","sec":18222},{"pos":487,"bib":555,"name":"ANNIE GOH","nat":"—","cat":"W 40–49","time":"05:04:30","sec":18270},{"pos":488,"bib":353,"name":"JANINE MORRIS","nat":"—","cat":"W 40–49","time":"05:06:13","sec":18373},{"pos":489,"bib":72,"name":"DOUGLAS BULL","nat":"—","cat":"M 20–39","time":"05:06:57","sec":18417},{"pos":490,"bib":308,"name":"CHRIS MAXWELL","nat":"—","cat":"W 50–59","time":"05:09:00","sec":18540},{"pos":491,"bib":586,"name":"PETER MACLEOD","nat":"—","cat":"M 20–39","time":"05:11:11","sec":18671},{"pos":492,"bib":397,"name":"FELICITY JANE POWELL","nat":"—","cat":"W 20–39","time":"05:11:52","sec":18712},{"pos":493,"bib":13,"name":"PAUL ANDERSON","nat":"—","cat":"M 50–59","time":"05:13:54","sec":18834},{"pos":494,"bib":510,"name":"GEORGE WIGGINS","nat":"—","cat":"M 60–69","time":"05:15:02","sec":18902},{"pos":495,"bib":326,"name":"AARON MCLACHLAN","nat":"—","cat":"M 40–49","time":"05:15:13","sec":18913},{"pos":496,"bib":152,"name":"HAYLEY ELKINS","nat":"—","cat":"W 40–49","time":"05:15:14","sec":18914},{"pos":497,"bib":553,"name":"ADRIANA ISTRATE","nat":"—","cat":"W 20–39","time":"05:16:51","sec":19011},{"pos":498,"bib":75,"name":"DAVE BYRNE","nat":"—","cat":"M 20–39","time":"05:17:11","sec":19031},{"pos":499,"bib":511,"name":"KAREN WIGGINS","nat":"—","cat":"W 50–59","time":"05:18:47","sec":19127},{"pos":500,"bib":17,"name":"PETER ANDREWS","nat":"—","cat":"M 60–69","time":"05:23:12","sec":19392},{"pos":501,"bib":142,"name":"STEVE DOUGHTY","nat":"—","cat":"M 50–59","time":"05:26:55","sec":19615},{"pos":502,"bib":518,"name":"LISA WILLIAMS","nat":"—","cat":"W 40–49","time":"05:27:16","sec":19636},{"pos":503,"bib":448,"name":"ASHLEY STEWART","nat":"—","cat":"W 20–39","time":"05:28:57","sec":19737},{"pos":504,"bib":360,"name":"CHARLOTTE NASEY","nat":"—","cat":"W 60–69","time":"05:29:29","sec":19769},{"pos":505,"bib":365,"name":"KRIS NICHOLSON","nat":"—","cat":"M 20–39","time":"05:29:30","sec":19770},{"pos":506,"bib":430,"name":"ANDREW SHELLEY","nat":"—","cat":"M 40–49","time":"05:29:36","sec":19776},{"pos":507,"bib":420,"name":"SHIRLEY ROLSTON","nat":"—","cat":"W 60–69","time":"05:30:45","sec":19845},{"pos":508,"bib":401,"name":"JOHN PRUE","nat":"—","cat":"M 50–59","time":"05:33:05","sec":19985},{"pos":509,"bib":358,"name":"SHELLEY MUSK","nat":"—","cat":"W 40–49","time":"05:36:34","sec":20194},{"pos":510,"bib":116,"name":"JANNA COWLEY","nat":"—","cat":"W 40–49","time":"05:41:45","sec":20505},{"pos":511,"bib":290,"name":"RAYMOND LUCAS","nat":"—","cat":"M 60–69","time":"05:45:04","sec":20704},{"pos":512,"bib":550,"name":"PHIL LAW","nat":"—","cat":"M 20–39","time":"05:51:06","sec":21066},{"pos":513,"bib":258,"name":"JIM KERSE","nat":"—","cat":"M 60–69","time":"05:54:47","sec":21287},{"pos":514,"bib":12,"name":"LINDA ANDERSON","nat":"—","cat":"W 50–59","time":"05:54:56","sec":21296},{"pos":515,"bib":11,"name":"EDWARD ANDERSON","nat":"—","cat":"M 50–59","time":"05:54:56","sec":21296}]